README.md
setup.py
magiceden_api/__init__.py
magiceden_api_parser.egg-info/PKG-INFO
magiceden_api_parser.egg-info/SOURCES.txt
magiceden_api_parser.egg-info/dependency_links.txt
magiceden_api_parser.egg-info/requires.txt
magiceden_api_parser.egg-info/top_level.txt